src/sha256_core.v
/**
  Module name: sha256_core
  Author: PTrujillo
  Date: Jan25
  Description: Computes SHA256 of byte array. Input limited to 55 bytes.
  Version: 1.0
  History:
    1.0 - Module created
**/

module sha256_core (
  input m_axis_aclk, 
  input m_axis_aresetn, 

  /* input data channel */
  input s_axis_tvalid,
  input [3:0] s_axis_tkeep,
  output reg s_axis_tready,
  input [31:0] s_axis_tdata,
  input s_axis_tlast,

  /* output data channel */
  output reg m_axis_tvalid,
  output wire [3:0] m_axis_tkeep,
  input m_axis_tready,
  output reg [31:0] m_axis_tdata,
  output reg m_axis_tlast
);

  localparam h0 = 32'b01101010000010011110011001100111;
  localparam h1 = 32'b10111011011001111010111010000101;
  localparam h2 = 32'b00111100011011101111001101110010;
  localparam h3 = 32'b10100101010011111111010100111010;
  localparam h4 = 32'b01010001000011100101001001111111;
  localparam h5 = 32'b10011011000001010110100010001100;
  localparam h6 = 32'b00011111100000111101100110101011;
  localparam h7 = 32'b01011011111000001100110100011001;

  localparam k0 = 32'b01000010100010100010111110011000;
  localparam k1 = 32'b01110001001101110100010010010001;
  localparam k2 = 32'b10110101110000001111101111001111;
  localparam k3 = 32'b11101001101101011101101110100101;
  localparam k4 = 32'b00111001010101101100001001011011;
  localparam k5 = 32'b01011001111100010001000111110001;
  localparam k6 = 32'b10010010001111111000001010100100;
  localparam k7 = 32'b10101011000111000101111011010101;
  localparam k8 = 32'b11011000000001111010101010011000;
  localparam k9 = 32'b00010010100000110101101100000001;
  localparam k10 = 32'b00100100001100011000010110111110;
  localparam k11 = 32'b01010101000011000111110111000011;
  localparam k12 = 32'b01110010101111100101110101110100;
  localparam k13 = 32'b10000000110111101011000111111110;
  localparam k14 = 32'b10011011110111000000011010100111;
  localparam k15 = 32'b11000001100110111111000101110100;
  localparam k16 = 32'b11100100100110110110100111000001;
  localparam k17 = 32'b11101111101111100100011110000110;
  localparam k18 = 32'b00001111110000011001110111000110;
  localparam k19 = 32'b00100100000011001010000111001100;
  localparam k20 = 32'b00101101111010010010110001101111;
  localparam k21 = 32'b01001010011101001000010010101010;
  localparam k22 = 32'b01011100101100001010100111011100;
  localparam k23 = 32'b01110110111110011000100011011010;
  localparam k24 = 32'b10011000001111100101000101010010;
  localparam k25 = 32'b10101000001100011100011001101101;
  localparam k26 = 32'b10110000000000110010011111001000;
  localparam k27 = 32'b10111111010110010111111111000111;
  localparam k28 = 32'b11000110111000000000101111110011;
  localparam k29 = 32'b11010101101001111001000101000111;
  localparam k30 = 32'b00000110110010100110001101010001;
  localparam k31 = 32'b00010100001010010010100101100111;
  localparam k32 = 32'b00100111101101110000101010000101;
  localparam k33 = 32'b00101110000110110010000100111000;
  localparam k34 = 32'b01001101001011000110110111111100;
  localparam k35 = 32'b01010011001110000000110100010011;
  localparam k36 = 32'b01100101000010100111001101010100;
  localparam k37 = 32'b01110110011010100000101010111011;
  localparam k38 = 32'b10000001110000101100100100101110;
  localparam k39 = 32'b10010010011100100010110010000101;
  localparam k40 = 32'b10100010101111111110100010100001;
  localparam k41 = 32'b10101000000110100110011001001011;
  localparam k42 = 32'b11000010010010111000101101110000;
  localparam k43 = 32'b11000111011011000101000110100011;
  localparam k44 = 32'b11010001100100101110100000011001;
  localparam k45 = 32'b11010110100110010000011000100100;
  localparam k46 = 32'b11110100000011100011010110000101;
  localparam k47 = 32'b00010000011010101010000001110000;
  localparam k48 = 32'b00011001101001001100000100010110;
  localparam k49 = 32'b00011110001101110110110000001000;
  localparam k50 = 32'b00100111010010000111011101001100;
  localparam k51 = 32'b00110100101100001011110010110101;
  localparam k52 = 32'b00111001000111000000110010110011;
  localparam k53 = 32'b01001110110110001010101001001010;
  localparam k54 = 32'b01011011100111001100101001001111;
  localparam k55 = 32'b01101000001011100110111111110011;
  localparam k56 = 32'b01110100100011111000001011101110;
  localparam k57 = 32'b01111000101001010110001101101111;
  localparam k58 = 32'b10000100110010000111100000010100;
  localparam k59 = 32'b10001100110001110000001000001000;
  localparam k60 = 32'b10010000101111101111111111111010;
  localparam k61 = 32'b10100100010100000110110011101011;
  localparam k62 = 32'b10111110111110011010001111110111;
  localparam k63 = 32'b11000110011100010111100011110010;

  reg [31:0] w_array [0:63];
  reg [31:0] w_index;
  wire [31:0] w_index_1;
  reg message_complete;
  wire [31:0] theta0;
  wire [31:0] theta1;

  reg [6:0] round;
  wire [31:0] k_round;

  reg [31:0] a_reg;
  reg [31:0] b_reg;
  reg [31:0] c_reg;
  reg [31:0] d_reg;
  reg [31:0] e_reg;
  reg [31:0] f_reg;
  reg [31:0] g_reg;
  reg [31:0] h_reg;

  reg [255:0] hash;

  wire [31:0] temp1;
  wire [31:0] temp2;
  wire [31:0] sum0;
  wire [31:0] sum1;
  wire [31:0] choice;
  wire [31:0] majority;

  integer i;

  assign w_index_1 = w_index + 32'd8;

  /* create the message chunk. Limited to 55 bytes */
  always @(posedge m_axis_aclk)
    if (!m_axis_aresetn || (round == 7'd71)) begin
      w_index <= 32'd0;
      for (i=0; i < 63; i=i+1) begin
        w_array[i] <= 32'd0;
      end
      message_complete <= 1'b0;
      s_axis_tready <= 1'b1;
    end
    else begin

      if (s_axis_tvalid && !message_complete) begin
        w_array[w_index[31:5]][(31-w_index[4:0])-:8] <= s_axis_tdata[7:0];

        if (s_axis_tlast) begin
          w_array[w_index_1[31:5]][(31-w_index_1[4:0])-:8] <= 8'b10000000;
          message_complete <= 1'b1;
          w_index = 32'd16;
        end
        else begin
          w_index <= w_index + 32'd8;
          w_array[15] <= w_index + 32'd16;
        end
      end
      else if (message_complete && (w_index < 32'd64)) begin
        w_array[w_index] <= w_array[w_index-16] + theta0 + w_array[w_index-7] + theta1;
        w_index <= w_index + 32'd1;
        s_axis_tready <= 1'b0;
      end
    end

  assign theta0 = {w_array[w_index-15][6:0], w_array[w_index-15][31:7]} ^ {w_array[w_index-15][17:0], w_array[w_index-15][31:18]} ^ {3'b000, w_array[w_index-15][31:3]};
  assign theta1 = {w_array[w_index-2][16:0], w_array[w_index-2][31:17]} ^ {w_array[w_index-2][18:0], w_array[w_index-2][31:19]} ^ {10'b0000000000, w_array[w_index-2][31:10]};
  
  assign sum0 = {a_reg[1:0], a_reg[31:2]} ^ {a_reg[12:0], a_reg[31:13]} ^ {a_reg[21:0], a_reg [31:22]};
  assign sum1 = {e_reg[5:0], e_reg[31:6]} ^ {e_reg[10:0], e_reg[31:11]} ^ {e_reg[24:0], e_reg[31:25]};
  assign choice = (e_reg & f_reg) ^ (~e_reg & g_reg);
  assign majority = (a_reg & b_reg) ^ (a_reg & c_reg) ^ (b_reg & c_reg);

  assign temp1  = h_reg + sum1 + choice + k_round + w_array[round];
  assign temp2 = sum0 + majority;

  always @(posedge m_axis_aclk) 
    if (!m_axis_aresetn || (!message_complete)) begin
      round <= 7'd0;
      a_reg <= h0;
      b_reg <= h1; 
      c_reg <= h2; 
      d_reg <= h3; 
      e_reg <= h4; 
      f_reg <= h5; 
      g_reg <= h6; 
      h_reg <= h7; 

      hash <= 256'd0;

      m_axis_tvalid <= 1'b0;
      m_axis_tlast <= 1'b0;
    end
    else  
      if (round < 64) begin
        a_reg <= temp1 + temp2;
        b_reg <= a_reg; 
        c_reg <= b_reg; 
        d_reg <= c_reg; 
        e_reg <= d_reg + temp1; 
        f_reg <= e_reg; 
        g_reg <= f_reg; 
        h_reg <= g_reg; 

        round <= round + 7'd1;
      end
      else if (round < 72) begin /* sending hash through AXI4 Stream */

        m_axis_tdata <= (round == 64)? a_reg+h0:
                        (round == 65)? b_reg+h1:
                        (round == 66)? c_reg+h2:
                        (round == 67)? d_reg+h3:
                        (round == 68)? e_reg+h4:
                        (round == 69)? f_reg+h5:
                        (round == 70)? g_reg+h6:
                        h_reg+h7;

        m_axis_tvalid <= 1'b1;

        if (round == 71)
          m_axis_tlast <= 1'b1;

        if (m_axis_tready)
          round <= round + 7'd1;

        hash <= {a_reg+h0, b_reg+h1, c_reg+h2, d_reg+h3, e_reg+h4, f_reg+h5, g_reg+h6, h_reg+h7};
      end
      else begin
         m_axis_tvalid <= 1'b0;
         m_axis_tlast <= 1'b0;
      end

  /* return K according round */
  assign k_round = (round == 7'd0)? k0:
                    (round == 7'd1)? k1:
                    (round == 7'd2)? k2:
                    (round == 7'd3)? k3:
                    (round == 7'd4)? k4:
                    (round == 7'd5)? k5:
                    (round == 7'd6)? k6:
                    (round == 7'd7)? k7:
                    (round == 7'd8)? k8:
                    (round == 7'd9)? k9:
                    (round == 7'd10)? k10:
                    (round == 7'd11)? k11:
                    (round == 7'd12)? k12:
                    (round == 7'd13)? k13:
                    (round == 7'd14)? k14:
                    (round == 7'd15)? k15:
                    (round == 7'd16)? k16:
                    (round == 7'd17)? k17:
                    (round == 7'd18)? k18:
                    (round == 7'd19)? k19:
                    (round == 7'd20)? k20:
                    (round == 7'd21)? k21:
                    (round == 7'd22)? k22:
                    (round == 7'd23)? k23:
                    (round == 7'd24)? k24:
                    (round == 7'd25)? k25:
                    (round == 7'd26)? k26:
                    (round == 7'd27)? k27:
                    (round == 7'd28)? k28:
                    (round == 7'd29)? k29:
                    (round == 7'd30)? k30:
                    (round == 7'd31)? k31:
                    (round == 7'd32)? k32:
                    (round == 7'd33)? k33:
                    (round == 7'd34)? k34:
                    (round == 7'd35)? k35:
                    (round == 7'd36)? k36:
                    (round == 7'd37)? k37:
                    (round == 7'd38)? k38:
                    (round == 7'd39)? k39:
                    (round == 7'd40)? k40:
                    (round == 7'd41)? k41:
                    (round == 7'd42)? k42:
                    (round == 7'd43)? k43:
                    (round == 7'd44)? k44:
                    (round == 7'd45)? k45:
                    (round == 7'd46)? k46:
                    (round == 7'd47)? k47:
                    (round == 7'd48)? k48:
                    (round == 7'd49)? k49:
                    (round == 7'd50)? k50:
                    (round == 7'd51)? k51:
                    (round == 7'd52)? k52:
                    (round == 7'd53)? k53:
                    (round == 7'd54)? k54:
                    (round == 7'd55)? k55:
                    (round == 7'd56)? k56:
                    (round == 7'd57)? k57:
                    (round == 7'd58)? k58:
                    (round == 7'd59)? k59:
                    (round == 7'd60)? k60:
                    (round == 7'd61)? k61:
                    (round == 7'd62)? k62:
                    k63;

endmodule

test/sha256_core_tb.sv
`timescale 1ns/1ns

`define clk_cycle 10

module sha256_core_tb ();


  reg aclk;
  reg aresetn;

  reg s_axis_tvalid;
  reg [3:0] s_axis_tkeep;
  wire s_axis_tready;
  reg [31:0] s_axis_tdata;
  reg s_axis_tlast;

  wire m_axis_tvalid;
  wire [3:0]  m_axis_tkeep;
  reg m_axis_tready;
  wire [31:0] m_axis_tdata;
  wire m_axis_tlast;

  reg [31:0] data_vector [4:0]; 

  integer w_array_0;
  integer w_array_1;
  integer w_array_2;
  integer w_array_3;
  integer w_array_4;
  integer w_array_5;
  integer w_array_6;
  integer w_array_7;
  integer w_array_8;
  integer w_array_9;
  integer w_array_10;
  integer w_array_11;
  integer w_array_12;
  integer w_array_13;
  integer w_array_14;
  integer w_array_15;
  integer w_array_16;
  integer w_array_17;
  integer w_array_18;
  integer w_array_19;
  integer w_array_20;
  integer w_array_21;
  integer w_array_22;
  integer w_array_23;
  integer w_array_24;
  integer w_array_25;
  integer w_array_26;
  integer w_array_27;
  integer w_array_28;
  integer w_array_29;
  integer w_array_30;
  integer w_array_31;
  integer w_array_32;
  integer w_array_33;
  integer w_array_34;
  integer w_array_35;
  integer w_array_36;
  integer w_array_37;
  integer w_array_38;
  integer w_array_39;
  integer w_array_40;
  integer w_array_41;
  integer w_array_42;
  integer w_array_43;
  integer w_array_44;
  integer w_array_45;
  integer w_array_46;
  integer w_array_47;
  integer w_array_48;
  integer w_array_49;
  integer w_array_50;
  integer w_array_51;
  integer w_array_52;
  integer w_array_53;
  integer w_array_54;
  integer w_array_55;
  integer w_array_56;
  integer w_array_57;
  integer w_array_58;
  integer w_array_59;
  integer w_array_60;
  integer w_array_61;
  integer w_array_62;
  integer w_array_63;


  integer i;

  initial begin
    aclk <= 1'b0;
    forever begin
      #(`clk_cycle/2);
      aclk <= ~aclk;
    end
  end

  sha256_core dut (
  .m_axis_aclk(aclk), 
  .m_axis_aresetn(aresetn), 
  /* input data channel */
  .s_axis_tvalid(s_axis_tvalid),
  .s_axis_tkeep(s_axis_tkeep),
  .s_axis_tready(s_axis_tready),
  .s_axis_tdata(s_axis_tdata),
  .s_axis_tlast(s_axis_tlast),
  /* output data channel */
  .m_axis_tvalid(m_axis_tvalid),
  .m_axis_tkeep(m_axis_tkeep),
  .m_axis_tready(m_axis_tready),
  .m_axis_tdata(m_axis_tdata),
  .m_axis_tlast(m_axis_tlast)
  );

  /* test flow */

  initial
    forever begin
      w_array_0 = dut.w_array[0];
      w_array_1 = dut.w_array[1];
      w_array_2 = dut.w_array[2];
      w_array_3 = dut.w_array[3];
      w_array_4 = dut.w_array[4];
      w_array_5 = dut.w_array[5];
      w_array_6 = dut.w_array[6];
      w_array_7 = dut.w_array[7];
      w_array_8 = dut.w_array[8];
      w_array_9 = dut.w_array[9];
      w_array_10 = dut.w_array[10];
      w_array_11 = dut.w_array[11];
      w_array_12 = dut.w_array[12];
      w_array_13 = dut.w_array[13];
      w_array_14 = dut.w_array[14];
      w_array_15 = dut.w_array[15];
      w_array_16 = dut.w_array[16];
      w_array_17 = dut.w_array[17];
      w_array_18 = dut.w_array[18];
      w_array_19 = dut.w_array[19];
      w_array_20 = dut.w_array[20];
      w_array_21 = dut.w_array[21];
      w_array_22 = dut.w_array[22];
      w_array_23 = dut.w_array[23];
      w_array_24 = dut.w_array[24];
      w_array_25 = dut.w_array[25];
      w_array_26 = dut.w_array[26];
      w_array_27 = dut.w_array[27];
      w_array_28 = dut.w_array[28];
      w_array_29 = dut.w_array[29];
      w_array_30 = dut.w_array[30];
      w_array_31 = dut.w_array[31];
      w_array_32 = dut.w_array[32];
      w_array_33 = dut.w_array[33];
      w_array_34 = dut.w_array[34];
      w_array_35 = dut.w_array[35];
      w_array_36 = dut.w_array[36];
      w_array_37 = dut.w_array[37];
      w_array_38 = dut.w_array[38];
      w_array_39 = dut.w_array[39];
      w_array_40 = dut.w_array[40];
      w_array_41 = dut.w_array[41];
      w_array_42 = dut.w_array[42];
      w_array_43 = dut.w_array[43];
      w_array_44 = dut.w_array[44];
      w_array_45 = dut.w_array[45];
      w_array_46 = dut.w_array[46];
      w_array_47 = dut.w_array[47];
      w_array_48 = dut.w_array[48];
      w_array_49 = dut.w_array[49];
      w_array_50 = dut.w_array[50];
      w_array_51 = dut.w_array[51];
      w_array_52 = dut.w_array[52];
      w_array_53 = dut.w_array[53];
      w_array_54 = dut.w_array[54];
      w_array_55 = dut.w_array[55];
      w_array_56 = dut.w_array[56];
      w_array_57 = dut.w_array[57];
      w_array_58 = dut.w_array[58];
      w_array_59 = dut.w_array[59];
      w_array_60 = dut.w_array[60];
      w_array_61 = dut.w_array[61];
      w_array_62 = dut.w_array[62];
      w_array_63 = dut.w_array[63];
      #(`clk_cycle/2);
    end
  initial begin

    $dumpfile ("data.vcd"); // Change filename as appropriate. 
    $dumpvars();

    i = 0;
    // data_vector[0] = 32'd104; /* h */
    // data_vector[1] = 32'd111; /* o */
    // data_vector[2] = 32'd108; /* l */
    // data_vector[3] = 32'd97; /* a */

    data_vector[0] = 32'd97; /* a */
    data_vector[1] = 32'd100; /* d */
    data_vector[2] = 32'd105; /* i */
    data_vector[3] = 32'd111; /* o */
    data_vector[4] = 32'd115; /* s */

    aresetn <= 1'b0;

    s_axis_tvalid <= 1'b0;
    s_axis_tkeep <= 4'b0000;
    s_axis_tdata <= 32'd0;
    s_axis_tlast <= 1'b0;

    m_axis_tready <= 1'b0;

    #(`clk_cycle*4);
    aresetn <= 1'b1;

    // @(posedge s_axis_tready);
    @(posedge aclk);

    s_axis_tvalid <= 1'b1;

    for (i = 0; i<=4; i=i+1) begin
      s_axis_tdata <= data_vector[i];
      if (i==4)
        s_axis_tlast <= 1'b1;

      @(posedge aclk);
      s_axis_tlast <= 1'b0;
    end

    s_axis_tvalid <= 1'b0;

    m_axis_tready <= 1'b1;
    @(posedge m_axis_tvalid);

    @(negedge m_axis_tvalid);
    m_axis_tready <= 1'b0;

    #(200*`clk_cycle);

    $finish;

  end

endmodule

test/data.vcd
$date
	Fri Jan 31 13:06:28 2025
$end
$version
	Icarus Verilog
$end
$timescale
	1ns
$end
$scope module sha256_core_tb $end
$var wire 4 ! m_axis_tkeep [3:0] $end
$var wire 1 " s_axis_tready $end
$var wire 1 # m_axis_tvalid $end
$var wire 1 $ m_axis_tlast $end
$var wire 32 % m_axis_tdata [31:0] $end
$var reg 1 & aclk $end
$var reg 1 ' aresetn $end
$var reg 1 ( m_axis_tready $end
$var reg 32 ) s_axis_tdata [31:0] $end
$var reg 4 * s_axis_tkeep [3:0] $end
$var reg 1 + s_axis_tlast $end
$var reg 1 , s_axis_tvalid $end
$var integer 32 - i [31:0] $end
$var integer 32 . w_array_0 [31:0] $end
$var integer 32 / w_array_1 [31:0] $end
$var integer 32 0 w_array_10 [31:0] $end
$var integer 32 1 w_array_11 [31:0] $end
$var integer 32 2 w_array_12 [31:0] $end
$var integer 32 3 w_array_13 [31:0] $end
$var integer 32 4 w_array_14 [31:0] $end
$var integer 32 5 w_array_15 [31:0] $end
$var integer 32 6 w_array_16 [31:0] $end
$var integer 32 7 w_array_17 [31:0] $end
$var integer 32 8 w_array_18 [31:0] $end
$var integer 32 9 w_array_19 [31:0] $end
$var integer 32 : w_array_2 [31:0] $end
$var integer 32 ; w_array_20 [31:0] $end
$var integer 32 < w_array_21 [31:0] $end
$var integer 32 = w_array_22 [31:0] $end
$var integer 32 > w_array_23 [31:0] $end
$var integer 32 ? w_array_24 [31:0] $end
$var integer 32 @ w_array_25 [31:0] $end
$var integer 32 A w_array_26 [31:0] $end
$var integer 32 B w_array_27 [31:0] $end
$var integer 32 C w_array_28 [31:0] $end
$var integer 32 D w_array_29 [31:0] $end
$var integer 32 E w_array_3 [31:0] $end
$var integer 32 F w_array_30 [31:0] $end
$var integer 32 G w_array_31 [31:0] $end
$var integer 32 H w_array_32 [31:0] $end
$var integer 32 I w_array_33 [31:0] $end
$var integer 32 J w_array_34 [31:0] $end
$var integer 32 K w_array_35 [31:0] $end
$var integer 32 L w_array_36 [31:0] $end
$var integer 32 M w_array_37 [31:0] $end
$var integer 32 N w_array_38 [31:0] $end
$var integer 32 O w_array_39 [31:0] $end
$var integer 32 P w_array_4 [31:0] $end
$var integer 32 Q w_array_40 [31:0] $end
$var integer 32 R w_array_41 [31:0] $end
$var integer 32 S w_array_42 [31:0] $end
$var integer 32 T w_array_43 [31:0] $end
$var integer 32 U w_array_44 [31:0] $end
$var integer 32 V w_array_45 [31:0] $end
$var integer 32 W w_array_46 [31:0] $end
$var integer 32 X w_array_47 [31:0] $end
$var integer 32 Y w_array_48 [31:0] $end
$var integer 32 Z w_array_49 [31:0] $end
$var integer 32 [ w_array_5 [31:0] $end
$var integer 32 \ w_array_50 [31:0] $end
$var integer 32 ] w_array_51 [31:0] $end
$var integer 32 ^ w_array_52 [31:0] $end
$var integer 32 _ w_array_53 [31:0] $end
$var integer 32 ` w_array_54 [31:0] $end
$var integer 32 a w_array_55 [31:0] $end
$var integer 32 b w_array_56 [31:0] $end
$var integer 32 c w_array_57 [31:0] $end
$var integer 32 d w_array_58 [31:0] $end
$var integer 32 e w_array_59 [31:0] $end
$var integer 32 f w_array_6 [31:0] $end
$var integer 32 g w_array_60 [31:0] $end
$var integer 32 h w_array_61 [31:0] $end
$var integer 32 i w_array_62 [31:0] $end
$var integer 32 j w_array_63 [31:0] $end
$var integer 32 k w_array_7 [31:0] $end
$var integer 32 l w_array_8 [31:0] $end
$var integer 32 m w_array_9 [31:0] $end
$scope module dut $end
$var wire 32 n choice [31:0] $end
$var wire 1 & m_axis_aclk $end
$var wire 1 ' m_axis_aresetn $end
$var wire 4 o m_axis_tkeep [3:0] $end
$var wire 1 ( m_axis_tready $end
$var wire 32 p majority [31:0] $end
$var wire 32 q s_axis_tdata [31:0] $end
$var wire 4 r s_axis_tkeep [3:0] $end
$var wire 1 + s_axis_tlast $end
$var wire 1 , s_axis_tvalid $end
$var wire 32 s sum0 [31:0] $end
$var wire 32 t sum1 [31:0] $end
$var wire 32 u theta0 [31:0] $end
$var wire 32 v theta1 [31:0] $end
$var wire 32 w w_index_1 [31:0] $end
$var wire 32 x temp2 [31:0] $end
$var wire 32 y temp1 [31:0] $end
$var wire 32 z k_round [31:0] $end
$var parameter 32 { h0 $end
$var parameter 32 | h1 $end
$var parameter 32 } h2 $end
$var parameter 32 ~ h3 $end
$var parameter 32 !" h4 $end
$var parameter 32 "" h5 $end
$var parameter 32 #" h6 $end
$var parameter 32 $" h7 $end
$var parameter 32 %" k0 $end
$var parameter 32 &" k1 $end
$var parameter 32 '" k10 $end
$var parameter 32 (" k11 $end
$var parameter 32 )" k12 $end
$var parameter 32 *" k13 $end
$var parameter 32 +" k14 $end
$var parameter 32 ," k15 $end
$var parameter 32 -" k16 $end
$var parameter 32 ." k17 $end
$var parameter 32 /" k18 $end
$var parameter 32 0" k19 $end
$var parameter 32 1" k2 $end
$var parameter 32 2" k20 $end
$var parameter 32 3" k21 $end
$var parameter 32 4" k22 $end
$var parameter 32 5" k23 $end
$var parameter 32 6" k24 $end
$var parameter 32 7" k25 $end
$var parameter 32 8" k26 $end
$var parameter 32 9" k27 $end
$var parameter 32 :" k28 $end
$var parameter 32 ;" k29 $end
$var parameter 32 <" k3 $end
$var parameter 32 =" k30 $end
$var parameter 32 >" k31 $end
$var parameter 32 ?" k32 $end
$var parameter 32 @" k33 $end
$var parameter 32 A" k34 $end
$var parameter 32 B" k35 $end
$var parameter 32 C" k36 $end
$var parameter 32 D" k37 $end
$var parameter 32 E" k38 $end
$var parameter 32 F" k39 $end
$var parameter 32 G" k4 $end
$var parameter 32 H" k40 $end
$var parameter 32 I" k41 $end
$var parameter 32 J" k42 $end
$var parameter 32 K" k43 $end
$var parameter 32 L" k44 $end
$var parameter 32 M" k45 $end
$var parameter 32 N" k46 $end
$var parameter 32 O" k47 $end
$var parameter 32 P" k48 $end
$var parameter 32 Q" k49 $end
$var parameter 32 R" k5 $end
$var parameter 32 S" k50 $end
$var parameter 32 T" k51 $end
$var parameter 32 U" k52 $end
$var parameter 32 V" k53 $end
$var parameter 32 W" k54 $end
$var parameter 32 X" k55 $end
$var parameter 32 Y" k56 $end
$var parameter 32 Z" k57 $end
$var parameter 32 [" k58 $end
$var parameter 32 \" k59 $end
$var parameter 32 ]" k6 $end
$var parameter 32 ^" k60 $end
$var parameter 32 _" k61 $end
$var parameter 32 `" k62 $end
$var parameter 32 a" k63 $end
$var parameter 32 b" k7 $end
$var parameter 32 c" k8 $end
$var parameter 32 d" k9 $end
$var reg 32 e" a_reg [31:0] $end
$var reg 32 f" b_reg [31:0] $end
$var reg 32 g" c_reg [31:0] $end
$var reg 32 h" d_reg [31:0] $end
$var reg 32 i" e_reg [31:0] $end
$var reg 32 j" f_reg [31:0] $end
$var reg 32 k" g_reg [31:0] $end
$var reg 32 l" h_reg [31:0] $end
$var reg 256 m" hash [255:0] $end
$var reg 32 n" m_axis_tdata [31:0] $end
$var reg 1 $ m_axis_tlast $end
$var reg 1 # m_axis_tvalid $end
$var reg 1 o" message_complete $end
$var reg 7 p" round [6:0] $end
$var reg 1 " s_axis_tready $end
$var reg 32 q" w_index [31:0] $end
$var integer 32 r" i [31:0] $end
$upscope $end
$upscope $end
$enddefinitions $end
$comment Show the parameter values. $end
$dumpall
b10010100000110101101100000001 d"
b11011000000001111010101010011000 c"
b10101011000111000101111011010101 b"
b11000110011100010111100011110010 a"
b10111110111110011010001111110111 `"
b10100100010100000110110011101011 _"
b10010000101111101111111111111010 ^"
b10010010001111111000001010100100 ]"
b10001100110001110000001000001000 \"
b10000100110010000111100000010100 ["
b1111000101001010110001101101111 Z"
b1110100100011111000001011101110 Y"
b1101000001011100110111111110011 X"
b1011011100111001100101001001111 W"
b1001110110110001010101001001010 V"
b111001000111000000110010110011 U"
b110100101100001011110010110101 T"
b100111010010000111011101001100 S"
b1011001111100010001000111110001 R"
b11110001101110110110000001000 Q"
b11001101001001100000100010110 P"
b10000011010101010000001110000 O"
b11110100000011100011010110000101 N"
b11010110100110010000011000100100 M"
b11010001100100101110100000011001 L"
b11000111011011000101000110100011 K"
b11000010010010111000101101110000 J"
b10101000000110100110011001001011 I"
b10100010101111111110100010100001 H"
b111001010101101100001001011011 G"
b10010010011100100010110010000101 F"
b10000001110000101100100100101110 E"
b1110110011010100000101010111011 D"
b1100101000010100111001101010100 C"
b1010011001110000000110100010011 B"
b1001101001011000110110111111100 A"
b101110000110110010000100111000 @"
b100111101101110000101010000101 ?"
b10100001010010010100101100111 >"
b110110010100110001101010001 ="
b11101001101101011101101110100101 <"
b11010101101001111001000101000111 ;"
b11000110111000000000101111110011 :"
b10111111010110010111111111000111 9"
b10110000000000110010011111001000 8"
b10101000001100011100011001101101 7"
b10011000001111100101000101010010 6"
b1110110111110011000100011011010 5"
b1011100101100001010100111011100 4"
b1001010011101001000010010101010 3"
b101101111010010010110001101111 2"
b10110101110000001111101111001111 1"
b100100000011001010000111001100 0"
b1111110000011001110111000110 /"
b11101111101111100100011110000110 ."
b11100100100110110110100111000001 -"
b11000001100110111111000101110100 ,"
b10011011110111000000011010100111 +"
b10000000110111101011000111111110 *"
b1110010101111100101110101110100 )"
b1010101000011000111110111000011 ("
b100100001100011000010110111110 '"
b1110001001101110100010010010001 &"
b1000010100010100010111110011000 %"
b1011011111000001100110100011001 $"
b11111100000111101100110101011 #"
b10011011000001010110100010001100 ""
b1010001000011100101001001111111 !"
b10100101010011111111010100111010 ~
b111100011011101111001101110010 }
b10111011011001111010111010000101 |
b1101010000010011110011001100111 {
$end
#0
$dumpvars
bx r"
bx q"
bx p"
xo"
bx n"
bx m"
bx l"
bx k"
bx j"
bx i"
bx h"
bx g"
bx f"
bx e"
bx z
bx y
bx x
bx w
bx v
bx u
bx t
bx s
b0 r
b0 q
bx p
bz o
bx n
bx m
bx l
bx k
bx j
bx i
bx h
bx g
bx f
bx e
bx d
bx c
bx b
bx a
bx `
bx _
bx ^
bx ]
bx \
bx [
bx Z
bx Y
bx X
bx W
bx V
bx U
bx T
bx S
bx R
bx Q
bx P
bx O
bx N
bx M
bx L
bx K
bx J
bx I
bx H
bx G
bx F
bx E
bx D
bx C
bx B
bx A
bx @
bx ?
bx >
bx =
bx <
bx ;
bx :
bx 9
bx 8
bx 7
bx 6
bx 5
bx 4
bx 3
bx 2
bx 1
bx 0
bx /
bx .
b0 -
0,
0+
b0 *
b0 )
0(
0'
0&
bx %
x$
x#
x"
bz !
$end
#5
b11110011011101111110110101101000 y
b110101100001110010011100101011 t
b1000100100001001101011100101 x
b11001110001000001011010001111110 s
b11111100001011100100110001100 n
b111010011011111110011001100111 p
b1000010100010100010111110011000 z
1"
0o"
b1000 w
b0 q"
0$
0#
b0 m"
b1011011111000001100110100011001 l"
b11111100000111101100110101011 k"
b10011011000001010110100010001100 j"
b1010001000011100101001001111111 i"
b10100101010011111111010100111010 h"
b111100011011101111001101110010 g"
b10111011011001111010111010000101 f"
b1101010000010011110011001100111 e"
b0 p"
b111111 r"
1&
#10
0&
b0 i
b0 h
b0 g
b0 e
b0 d
b0 c
b0 b
b0 a
b0 `
b0 _
b0 ^
b0 ]
b0 \
b0 Z
b0 Y
b0 X
b0 W
b0 V
b0 U
b0 T
b0 S
b0 R
b0 Q
b0 O
b0 N
b0 M
b0 L
b0 K
b0 J
b0 I
b0 H
b0 G
b0 F
b0 D
b0 C
b0 B
b0 A
b0 @
b0 ?
b0 >
b0 =
b0 <
b0 ;
b0 9
b0 8
b0 7
b0 6
b0 5
b0 4
b0 3
b0 2
b0 1
b0 0
b0 m
b0 l
b0 k
b0 f
b0 [
b0 P
b0 E
b0 :
b0 /
b0 .
#15
b111111 r"
1&
#20
0&
#25
b111111 r"
1&
#30
0&
#35
b111111 r"
1&
#40
0&
1'
#45
b1100001 )
b1100001 q
1,
1&
#50
0&
#55
b0 v
b1100100 )
b1100100 q
b10000 w
b1000 q"
b1010100011101111110110101101000 y
b1 -
1&
#60
0&
b10000 5
b1100001000000000000000000000000 .
#65
b0 u
b11000 w
b10000 q"
b1010100110110111110110101101000 y
b1101001 )
b1101001 q
b10 -
1&
#70
0&
b11000 5
b1100001011001000000000000000000 .
#75
b1101111 )
b1101111 q
b100000 w
b11000 q"
b1010100110111000101011001101000 y
b11 -
1&
#80
0&
b100000 5
b1100001011001000110100100000000 .
#85
b101000 w
b100000 q"
b1010100110111000101011011010111 y
1+
b1110011 )
b1110011 q
b100 -
1&
#90
0&
b101000 5
b1100001011001000110100101101111 .
#95
b1110100101110001110011100000 u
1(
0,
0+
1o"
b101 -
b11000 w
b10000 q"
1&
#100
0&
b1110011100000000000000000000000 /
#105
b100010000000000000000 v
b0 u
b11010011111100011111110001000100 t
b1010001000011010110000010011101 n
b1111011011011011110011010100101 p
b10100100111011010000110100100010 x
b101001011111110010011001111101 s
b1110001001101110100010010010001 z
0"
b11001 w
b10001 q"
b1 p"
b101001001110100111101100011101 y
b11111100000111101100110101011 l"
b10011011000001010110100010001100 k"
b1010001000011100101001001111111 j"
b11111010001011000100110000010001 i"
b111100011011101111001101110010 h"
b10111011011001111010111010000101 g"
b1101010000010011110011001100111 f"
b1011101011011001111000110111100 e"
1&
#110
0&
b1101111111110111000011001001111 6
